aps_automation_sdk/__init__.py
aps_automation_sdk/acc.py
aps_automation_sdk/classes.py
aps_automation_sdk/core.py
aps_automation_sdk/dsl.py
aps_automation_sdk/model_derivative.py
aps_automation_sdk/utils.py
aps_automation_sdk-0.1.1.dist-info/METADATA
aps_automation_sdk-0.1.1.dist-info/WHEEL
aps_automation_sdk-0.1.1.dist-info/licenses/LICENSE
aps_automation_sdk-0.1.1.dist-info/RECORD
