Metadata-Version: 2.4
Name: aps-automation-sdk
Version: 0.1.1
Summary: Python SDK for Autodesk Platform Services Automation API
Project-URL: repository, https://github.com/viktor-platform/aps-automation-sdk
Author-email: Alejandro Duarte <alejandroduartevendries@gmail.com>, Stijn Jansen <sjansen@viktor.ai>
License: MIT
License-File: LICENSE
Requires-Python: >=3.11
Requires-Dist: pydantic>=2.12.3
Requires-Dist: python-dotenv>=1.2.1
Requires-Dist: requests>=2.32.5
Provides-Extra: examples
Requires-Dist: ipykernel>=7.1.0; extra == 'examples'
